preprocessing/AdjustedScaler.py
preprocessing/__init__.py
smart_data_tools-0.3.1.dist-info/LICENSE
smart_data_tools-0.3.1.dist-info/METADATA
smart_data_tools-0.3.1.dist-info/WHEEL
smart_data_tools-0.3.1.dist-info/top_level.txt
smart_data_tools-0.3.1.dist-info/RECORD
