Metadata-Version: 2.1
Name: smart-data-tools
Version: 0.3.1
Summary: This library contains adjusted tools for data preprocessing and working with mixed data types.
Home-page: https://github.com/newchronik/smart-data-tools
Author: Anton Kvasnitsa
Author-email: anton.kvasnitsa@gmail.com
License: MIT
Keywords: data preprocessing scaler
Platform: UNKNOWN
Requires-Dist: numpy
Requires-Dist: pandas
